fraud_detection_autoencoders/__init__.py
fraud_detection_autoencoders/_nbdev.py
fraud_detection_autoencoders/core.py
fraud_detection_autoencoders-1.0.1.dist-info/LICENSE.md
fraud_detection_autoencoders-1.0.1.dist-info/METADATA
fraud_detection_autoencoders-1.0.1.dist-info/WHEEL
fraud_detection_autoencoders-1.0.1.dist-info/entry_points.txt
fraud_detection_autoencoders-1.0.1.dist-info/top_level.txt
fraud_detection_autoencoders-1.0.1.dist-info/RECORD
