Metadata-Version: 2.1
Name: fraud-detection-autoencoders
Version: 1.0.1
Summary: Use autoencoders to detect fraud samples.
Home-page: https://github.com/JiaxiangBU/fraud_detection_autoencoders
Author: Jiaxiang Li
Author-email: alex.lijiaxiang@foxmail.com
License: Apache Software License 2.0
Keywords: autoencoder fraud
Platform: UNKNOWN
Classifier: Development Status :: 3 - Alpha
Classifier: Intended Audience :: Developers
Classifier: License :: OSI Approved :: Apache Software License
Classifier: Natural Language :: English
Classifier: Programming Language :: Python :: 3.6
Classifier: Programming Language :: Python :: 3.7
Classifier: Programming Language :: Python :: 3.8
Requires-Python: >=3.6
